splitlogger/__init__.py
splitlogger/logger.py
splitlogger-1.0.3.dist-info/METADATA
splitlogger-1.0.3.dist-info/WHEEL
splitlogger-1.0.3.dist-info/top_level.txt
splitlogger-1.0.3.dist-info/RECORD
