Metadata-Version: 2.1
Name: splitlogger
Version: 1.0.3
Summary: encapsulate logger
Home-page: UNKNOWN
Author: Jayson
Author-email: jaysonteng@163.com
License: UNKNOWN
Platform: UNKNOWN
Requires-Python: >=3.*.*
